sqldol/__init__.py
sqldol/base.py
sqldol/sql_base.py
sqldol/util.py
sqldol/scrap/__init__.py
sqldol/scrap/postgres_dol.py
sqldol/tests/__init__.py
sqldol/tests/base_test.py
sqldol/tests/mk_test_data.py
sqldol/tests/test_sql_w_sqlalchemy.py
sqldol-0.1.3.dist-info/LICENSE
sqldol-0.1.3.dist-info/METADATA
sqldol-0.1.3.dist-info/WHEEL
sqldol-0.1.3.dist-info/top_level.txt
sqldol-0.1.3.dist-info/RECORD
