Metadata-Version: 2.1
Name: sqldol
Version: 0.1.3
Summary: sql (through sqlalchemy) with a simple (dict-like or list-like) interface
Home-page: https://github.com/i2mint/sqldol
Author: OtoSense
License: apache-2.0
Platform: any
License-File: LICENSE
Requires-Dist: dol
Requires-Dist: sqlalchemy
